outline/__init__.py
outline/client.py
outline/exceptions.py
python_outline-1.0.1.dist-info/LICENSE
python_outline-1.0.1.dist-info/METADATA
python_outline-1.0.1.dist-info/WHEEL
python_outline-1.0.1.dist-info/top_level.txt
python_outline-1.0.1.dist-info/RECORD
