Metadata-Version: 2.1
Name: python-outline
Version: 1.0.1
Summary: Simple and easy to use wrapper for the Outline API.
Author-email: Vladislav Fedin <vlad@fedin7.ru>
License: MIT License
Project-URL: Documentation, https://python-outline.readthedocs.io/
Project-URL: Repository, https://github.com/7vlad7/python-outline.git
Project-URL: Issues, https://github.com/7vlad7/python-outline/issues
Keywords: python,python3,outline,outline vpn,shadowsocks
Classifier: Development Status :: 5 - Production/Stable
Classifier: Intended Audience :: Developers
Classifier: License :: OSI Approved :: MIT License
Classifier: Programming Language :: Python :: 3
Classifier: Programming Language :: Python :: 3.7
Classifier: Programming Language :: Python :: 3.8
Classifier: Programming Language :: Python :: 3.10
Classifier: Programming Language :: Python :: 3.11
Classifier: Programming Language :: Python :: 3.12
Requires-Python: >=3.7
License-File: LICENSE
Requires-Dist: httpx ==0.26.0
